{"schema":"rp-knowledge-graph-v1","campaignId":"world-library","cardId":"absolute-duo","nodes":[{"id":"kg-blaze","type":"power-system","title":"焰牙","aliases":["Blaze"],"visibility":"public","summary":"灵魂武装具现。","fullText":"黎明星纹适合者能显现灵魂武器。","tags":["soul","weapon"],"importance":"critical","source":{"kind":"worldbook","ref":"src-absolute-duo-001"},"revealConditions":[],"evidenceLevel":"B","contradictedBy":[],"metadata":{}},{"id":"kg-duo","type":"rule","title":"双刃制度","aliases":[],"visibility":"public","summary":"学生组成二人搭档训练与作战。","fullText":"搭档关系决定训练、战术和情感线。","tags":["academy","partner"],"importance":"high","source":{"kind":"worldbook","ref":"src-absolute-duo-001"},"revealConditions":[],"evidenceLevel":"B","contradictedBy":[],"metadata":{}},{"id":"kg-tooru-shield","type":"fact","title":"透流的盾焰牙","aliases":[],"visibility":"public","summary":"透流焰牙为盾，是体系例外。","fullText":"盾形态使其定位偏防御与守护。","tags":["exception"],"importance":"high","source":{"kind":"worldbook","ref":"src-absolute-duo-001"},"revealConditions":[],"evidenceLevel":"B","contradictedBy":[],"metadata":{}}],"edges":[{"id":"e-blaze-duo","from":"kg-blaze","to":"kg-duo","type":"supports","visibility":"public","strength":{"level":"A","score":80,"description":"双刃围绕焰牙训练。"},"description":"焰牙体系支撑学园制度。","gmNotes":""}],"indices":{"byVisibility":{"public":["kg-blaze","kg-duo","kg-tooru-shield"]},"byType":{"power-system":["kg-blaze"],"rule":["kg-duo"],"fact":["kg-tooru-shield"]},"byTag":{"soul":["kg-blaze"],"partner":["kg-duo"],"exception":["kg-tooru-shield"]},"activeClues":[],"lockedSecrets":[]}}